graia/scheduler/__init__.py
graia/scheduler/creator.py
graia/scheduler/exception.py
graia/scheduler/saya/__init__.py
graia/scheduler/saya/behaviour.py
graia/scheduler/saya/schema.py
graia/scheduler/saya/shortcut.py
graia/scheduler/service.py
graia/scheduler/task.py
graia/scheduler/timers.py
graia/scheduler/utilles.py
graia_scheduler-0.3.1.dist-info/METADATA
graia_scheduler-0.3.1.dist-info/WHEEL
graia_scheduler-0.3.1.dist-info/entry_points.txt
graia_scheduler-0.3.1.dist-info/RECORD
