Metadata-Version: 2.1
Name: graia-scheduler
Version: 0.3.1
Summary: a scheduler for graia framework
Author-Email: GreyElaina <31543961+GreyElaina@users.noreply.github.com>
License: MIT
Requires-Python: <4.0,>=3.8
Requires-Dist: graia-broadcast~=0.23.0
Requires-Dist: croniter<2.0.0,>=1.0.0
Requires-Dist: launart>=0.7.0
Requires-Dist: creart~=0.3.0
Requires-Dist: graia-saya<0.1,>=0.0.16; extra == "saya"
Provides-Extra: saya
